mtl/__init__.py
mtl/ast.py
mtl/evaluator.py
mtl/hypothesis.py
mtl/parser.py
mtl/sugar.py
mtl/test_ast.py
mtl/test_boolean_eval.py
mtl/test_eval.py
mtl/test_params.py
mtl/test_parser.py
mtl/test_utils.py
mtl/utils.py
metric_temporal_logic-0.4.0.dist-info/LICENSE
metric_temporal_logic-0.4.0.dist-info/WHEEL
metric_temporal_logic-0.4.0.dist-info/METADATA
metric_temporal_logic-0.4.0.dist-info/RECORD
