Metadata-Version: 2.1
Name: metric-temporal-logic
Version: 0.4.0
Summary: A library for manipulating and evaluating metric temporal logic.
Home-page: https://github.com/mvcisback/py-metric-temporal-logic
License: MIT
Author: Marcell Vazquez-Chanlatte
Author-email: mvc@linux.com
Requires-Python: >=3.7,<4.0
Classifier: License :: OSI Approved :: MIT License
Classifier: Programming Language :: Python :: 3
Classifier: Programming Language :: Python :: 3.10
Classifier: Programming Language :: Python :: 3.7
Classifier: Programming Language :: Python :: 3.8
Classifier: Programming Language :: Python :: 3.9
Requires-Dist: attrs (>=22,<23)
Requires-Dist: discrete-signals (>=0.7.3,<0.8.0)
Requires-Dist: lenses (>=0.5.0,<0.6.0)
Requires-Dist: parsimonious (>=0.8.1,<0.9.0)
Project-URL: Repository, https://github.com/mvcisback/py-metric-temporal-logic
